{
  "users": [
    {
      "firstName": "homer",
      "lastName": "simpson",
      "email": "a",
      "password": "a",
      "id": "3ad52697-6d98-4d80-8273-084de55a86c0"
    },
    {
      "firstName": "marge",
      "lastName": "simpson",
      "email": "b",
      "password": "b",
      "id": "2b6f0989-7b7f-4a38-ad26-aa06b922d751"
    },
    {
      "firstName": "a",
      "lastName": "b",
      "email": "a",
      "password": "q",
      "id": "cd820ec5-ed05-4ccb-bd06-557329b280f5"
    },
    {
      "firstName": "a",
      "lastName": "a",
      "email": "a",
      "password": "a",
      "id": "cfb79a21-bee6-4137-ac6f-be831b671f25"
    },
    {
      "firstName": "a",
      "lastName": "a",
      "email": " ",
      "password": " ",
      "id": "b1e935ab-8bbe-45a4-9087-da877e0086b6"
    },
    {
      "firstName": "",
      "lastName": "",
      "email": "",
      "password": "",
      "id": "2f439f32-0fc9-4efe-8481-eaf84cbd7e0f"
    },
    {
      "firstName": "Leanne",
      "lastName": "Dunne",
      "email": "leanned97@icloud.com",
      "password": "Leanne0904",
      "id": "ff08707a-160e-4862-ace8-c1cb429f988c"
    },
    {
      "firstName": "Leanne",
      "lastName": "Dunne",
      "email": "leanned97@icloud.com",
      "password": "Leanne0904",
      "id": "805d183d-7ec7-4bda-aa23-4b7d930a2e6a"
    }
  ]
}